{
  "mappings": [
    {
      "source": "cl_recid",
      "target": "_record_id",
      "type": "rename",
      "rationale": "COBOL abbreviation expanded: cl_recid -> _record_id",
      "confidence": 0.85,
      "table": "claimants"
    },
    {
      "source": "cl_fnam",
      "target": "first_name",
      "type": "rename",
      "rationale": "COBOL abbreviation expanded: cl_fnam -> first_name",
      "confidence": 0.85,
      "table": "claimants"
    },
    {
      "source": "cl_lnam",
      "target": "last_name",
      "type": "rename",
      "rationale": "COBOL abbreviation expanded: cl_lnam -> last_name",
      "confidence": 0.85,
      "table": "claimants"
    },
    {
      "source": "cl_ssn",
      "target": "ssn_hash",
      "type": "transform",
      "rationale": "SHA-256 hash for HIPAA compliance \u2014 raw SSN must NEVER be written to modern system; duplicate SSNs indicate identity conflicts requiring manual resolution before migration proceeds",
      "confidence": 1.0,
      "table": "claimants"
    },
    {
      "source": "cl_dob",
      "target": "date_of_birth",
      "type": "rename",
      "rationale": "COBOL abbreviation expanded: cl_dob -> date_of_birth",
      "confidence": 0.85,
      "table": "claimants"
    },
    {
      "source": "cl_phon",
      "target": "phone_number",
      "type": "rename",
      "rationale": "COBOL abbreviation expanded: cl_phon -> phone_number",
      "confidence": 0.85,
      "table": "claimants"
    },
    {
      "source": "cl_emal",
      "target": "email",
      "type": "rename",
      "rationale": "COBOL abbreviation expanded: cl_emal -> email",
      "confidence": 0.85,
      "table": "claimants"
    },
    {
      "source": "cl_adr1",
      "target": "address_line1",
      "type": "rename",
      "rationale": "COBOL abbreviation expanded: cl_adr1 -> address_line1",
      "confidence": 0.85,
      "table": "claimants"
    },
    {
      "source": "cl_city",
      "target": "city",
      "type": "rename",
      "rationale": "COBOL abbreviation expanded: cl_city -> city",
      "confidence": 0.85,
      "table": "claimants"
    },
    {
      "source": "cl_st",
      "target": "state",
      "type": "rename",
      "rationale": "COBOL abbreviation expanded: cl_st -> state",
      "confidence": 0.85,
      "table": "claimants"
    },
    {
      "source": "cl_zip",
      "target": "zip_code",
      "type": "rename",
      "rationale": "COBOL abbreviation expanded: cl_zip -> zip_code",
      "confidence": 0.85,
      "table": "claimants"
    },
    {
      "source": "cl_bact",
      "target": null,
      "type": "archived",
      "rationale": "Bank account number NOT migrated \u2014 PCI-DSS regulated financial identifier; must be archived to encrypted vault and claimants re-enrolled through secure portal. Archive alongside cl_brtn. Any plaintext exposure is a PCI-DSS Level 1 violation. Do NOT include in ETL pipeline.",
      "confidence": 1.0,
      "table": "claimants"
    },
    {
      "source": "cl_brtn",
      "target": null,
      "type": "archived",
      "rationale": "Bank routing number NOT migrated \u2014 PCI-DSS regulated financial identifier. Archive alongside cl_bact to encrypted vault. Routing numbers combined with account numbers constitute full banking credentials \u2014 any plaintext exposure is a PCI-DSS Level 1 violation. Do NOT include in ETL pipeline.",
      "confidence": 1.0,
      "table": "claimants"
    },
    {
      "source": "cl_stat",
      "target": "claimant_status",
      "type": "transform",
      "rationale": "Status codes normalised: 'ACTIVE'->'active', 'INACTIVE'->'inactive', 'SUSPENDED'->'suspended'. Legacy freetext values must be mapped; unmapped values default to 'pending_review' and flagged for manual triage.",
      "confidence": 1.0,
      "table": "claimants"
    },
    {
      "source": "cl_rgdt",
      "target": "registered_at",
      "type": "rename",
      "rationale": "COBOL abbreviation expanded: cl_rgdt -> registered_at",
      "confidence": 0.85,
      "table": "claimants"
    },
    {
      "source": "cl_dcsd",
      "target": "is_deceased",
      "type": "rename",
      "rationale": "COBOL abbreviation expanded: cl_dcsd -> is_deceased",
      "confidence": 0.85,
      "table": "claimants"
    },
    {
      "source": "cl_fil1",
      "target": null,
      "type": "removed",
      "rationale": "Legacy filler/padding field with no business meaning \u2014 safe to drop. Verify no application code reads this field before finalising ETL.",
      "confidence": 1.0,
      "table": "claimants"
    },
    {
      "source": "er_recid",
      "target": "employer_id",
      "type": "transform",
      "rationale": "er_recid (legacy integer sequence) migrated to UUID-based employer_id in modern system; ETL must generate stable UUIDs and update all FK references in claims and payments before cutover.",
      "confidence": 1.0,
      "table": "employers"
    },
    {
      "source": "er_name",
      "target": "name",
      "type": "rename",
      "rationale": "COBOL abbreviation expanded: er_name -> name",
      "confidence": 0.85,
      "table": "employers"
    },
    {
      "source": "er_ein",
      "target": "ein",
      "type": "rename",
      "rationale": "COBOL abbreviation expanded: er_ein -> ein",
      "confidence": 0.85,
      "table": "employers"
    },
    {
      "source": "er_ind",
      "target": "industry",
      "type": "rename",
      "rationale": "COBOL abbreviation expanded: er_ind -> industry",
      "confidence": 0.85,
      "table": "employers"
    },
    {
      "source": "er_adr1",
      "target": "address_line1",
      "type": "rename",
      "rationale": "COBOL abbreviation expanded: er_adr1 -> address_line1",
      "confidence": 0.85,
      "table": "employers"
    },
    {
      "source": "er_city",
      "target": "city",
      "type": "rename",
      "rationale": "COBOL abbreviation expanded: er_city -> city",
      "confidence": 0.85,
      "table": "employers"
    },
    {
      "source": "er_st",
      "target": "state",
      "type": "rename",
      "rationale": "COBOL abbreviation expanded: er_st -> state",
      "confidence": 0.85,
      "table": "employers"
    },
    {
      "source": "er_zip",
      "target": "zip_code",
      "type": "rename",
      "rationale": "COBOL abbreviation expanded: er_zip -> zip_code",
      "confidence": 0.85,
      "table": "employers"
    },
    {
      "source": "er_phon",
      "target": "phone_number",
      "type": "rename",
      "rationale": "COBOL abbreviation expanded: er_phon -> phone_number",
      "confidence": 0.85,
      "table": "employers"
    },
    {
      "source": "er_stat",
      "target": "employer_status",
      "type": "transform",
      "rationale": "Employer status codes normalised to modern enum values; legacy freetext statuses require mapping table review before ETL runs.",
      "confidence": 1.0,
      "table": "employers"
    },
    {
      "source": "cm_recid",
      "target": "_record_id",
      "type": "rename",
      "rationale": "COBOL abbreviation expanded: cm_recid -> _record_id",
      "confidence": 0.85,
      "table": "claims"
    },
    {
      "source": "cm_clmnt",
      "target": "claimant_id",
      "type": "rename",
      "rationale": "COBOL abbreviation expanded: cm_clmnt -> claimant_id",
      "confidence": 0.85,
      "table": "claims"
    },
    {
      "source": "cm_emplr",
      "target": "employer_id",
      "type": "rename",
      "rationale": "Renamed to employer_id as FK to employers table; orphan risk if employer records not fully migrated first \u2014 run employer migration before claims ETL.",
      "confidence": 1.0,
      "table": "claims"
    },
    {
      "source": "cm_seprs",
      "target": "separation_reason",
      "type": "rename",
      "rationale": "COBOL abbreviation expanded: cm_seprs -> separation_reason",
      "confidence": 0.85,
      "table": "claims"
    },
    {
      "source": "cm_fildt",
      "target": "filing_date",
      "type": "rename",
      "rationale": "COBOL abbreviation expanded: cm_fildt -> filing_date",
      "confidence": 0.85,
      "table": "claims"
    },
    {
      "source": "cm_bystr",
      "target": "benefit_year_start",
      "type": "transform",
      "rationale": "Renamed from cm_bystr to benefit_year_start; date format normalised from YYYYMMDD integer to ISO-8601 date string \u2014 ETL must parse and reformat all values.",
      "confidence": 1.0,
      "table": "claims"
    },
    {
      "source": "cm_byend",
      "target": "benefit_year_end",
      "type": "rename",
      "rationale": "COBOL abbreviation expanded: cm_byend -> benefit_year_end",
      "confidence": 0.85,
      "table": "claims"
    },
    {
      "source": "cm_wkamt",
      "target": "weekly_benefit_amount",
      "type": "rename",
      "rationale": "COBOL abbreviation expanded: cm_wkamt -> weekly_benefit_amount",
      "confidence": 0.85,
      "table": "claims"
    },
    {
      "source": "cm_mxamt",
      "target": "max_benefit_amount",
      "type": "rename",
      "rationale": "COBOL abbreviation expanded: cm_mxamt -> max_benefit_amount",
      "confidence": 0.85,
      "table": "claims"
    },
    {
      "source": "cm_totpd",
      "target": "total_paid",
      "type": "rename",
      "rationale": "COBOL abbreviation expanded: cm_totpd -> total_paid",
      "confidence": 0.85,
      "table": "claims"
    },
    {
      "source": "cm_wkcnt",
      "target": "weeks_claimed",
      "type": "rename",
      "rationale": "COBOL abbreviation expanded: cm_wkcnt -> weeks_claimed",
      "confidence": 0.85,
      "table": "claims"
    },
    {
      "source": "cm_stat",
      "target": "claim_status",
      "type": "transform",
      "rationale": "Claim status normalised to modern enum; CRITICAL business rule: claims with cm_stat='PAID' where cm_totpd < cm_mxamt indicate potential overpayment \u2014 flag for compliance review before migration completes.",
      "confidence": 1.0,
      "table": "claims"
    },
    {
      "source": "cm_lupdt",
      "target": "updated_at",
      "type": "rename",
      "rationale": "COBOL abbreviation expanded: cm_lupdt -> updated_at",
      "confidence": 0.85,
      "table": "claims"
    },
    {
      "source": "bp_recid",
      "target": "_record_id",
      "type": "rename",
      "rationale": "COBOL abbreviation expanded: bp_recid -> _record_id",
      "confidence": 0.85,
      "table": "benefit_payments"
    },
    {
      "source": "bp_clmid",
      "target": "claim_id",
      "type": "rename",
      "rationale": "COBOL abbreviation expanded: bp_clmid -> claim_id",
      "confidence": 0.85,
      "table": "benefit_payments"
    },
    {
      "source": "bp_paydt",
      "target": "payment_date",
      "type": "rename",
      "rationale": "COBOL abbreviation expanded: bp_paydt -> payment_date",
      "confidence": 0.85,
      "table": "benefit_payments"
    },
    {
      "source": "bp_payam",
      "target": "payment_amount",
      "type": "rename",
      "rationale": "COBOL abbreviation expanded: bp_payam -> payment_amount",
      "confidence": 0.85,
      "table": "benefit_payments"
    },
    {
      "source": "bp_methd",
      "target": "method",
      "type": "rename",
      "rationale": "COBOL abbreviation expanded: bp_methd -> method",
      "confidence": 0.85,
      "table": "benefit_payments"
    },
    {
      "source": "bp_wkedt",
      "target": "week_ending_date",
      "type": "rename",
      "rationale": "COBOL abbreviation expanded: bp_wkedt -> week_ending_date",
      "confidence": 0.85,
      "table": "benefit_payments"
    },
    {
      "source": "bp_stat",
      "target": "payment_status",
      "type": "transform",
      "rationale": "Payment status normalised to modern enum values ('ISSUED', 'CLEARED', 'VOIDED'); legacy 'CANC' code maps to 'VOIDED' \u2014 validate all payment records before and after transform.",
      "confidence": 1.0,
      "table": "benefit_payments"
    },
    {
      "source": "bp_chkno",
      "target": "check_number",
      "type": "rename",
      "rationale": "COBOL abbreviation expanded: bp_chkno -> check_number",
      "confidence": 0.85,
      "table": "benefit_payments"
    }
  ]
}